{
    "json_file_name": "F:\\Ask_Information\\内科\\血液内科\\血小板减少性紫癜\\https_$$www.120ask.com$question$60009290.htm.json",
    "Description": "男宝宝，3个月了，由于湿疹严重去医院检查过敏原，结果如下，帮忙看下！过敏结果:花生 0.36  参考值是0.35其他都好免疫球蛋白G   3.20   参考值4.5-5.0免疫球蛋白A   0.07   参考值0.1-0.4:",
    "Cut_Description": "男 / 宝宝 / ， / 3 / 个 / 月 / 了 / ， / 由于 / 湿疹 / 严重 / 去 / 医院 / 检查 / 过敏原 / ， / 结果 / 如下 / ， / 帮忙 / 看 / 下 / ！ / 过敏 / 结果 / : / 花生 /   / 0.36 /   /   / 参考值 / 是 / 0.35 / 其他 / 都 / 好 / 免疫 / 球蛋白 / G /   /   /   / 3.20 /   /   /   / 参考值 / 4.5 / - / 5.0 / 免疫 / 球蛋白 / A /   /   /   / 0.07 /   /   /   / 参考值 / 0.1 / - / 0.4 / :",
    "Count_Medical_Des": "1",
    "Word_Medical_Desc": "过敏原 ",
    "Count_Desease_Des": "1",
    "Word_Desease_Desc": "湿疹 ",
    "Reply_Information": [
        {
            "Doctor_Reply": "病情分析：这个是检查结果都是比较正常的，只是花生的结果是稍高，注意避免接触过多就可以了的，比较低影响不大指导意见：建议如果是没有其他的症状，那么注意不要吃花生就可以了 ",
            "Cut_Doctor_Reply": "病情 / 分析 / ： / 这个 / 是 / 检查 / 结果 / 都 / 是 / 比较 / 正常 / 的 / ， / 只是 / 花生 / 的 / 结果 / 是 / 稍 / 高 / ， / 注意 / 避免 / 接触 / 过多 / 就 / 可以 / 了 / 的 / ， / 比较 / 低 / 影响 / 不 / 大 / 指导 / 意见 / ： / 建议 / 如果 / 是 / 没有 / 其他 / 的 / 症状 / ， / 那么 / 注意 / 不要 / 吃 / 花生 / 就 / 可以 / 了 /  ",
            "Count_Medical_Des": "0",
            "Word_Medical_Desc": "",
            "Count_Desease_Des": "0",
            "Word_Desease_Desc": ""
        },
        {
            "Doctor_Reply": "病情分析：你好，目前从你提供的这个情况来看的话，意义并不是很大的，你不必太担心的，目前你都是怎么治疗的？治疗效果呢？指导意见：要是从你提供的这个情况来看的话，建议你不要吃花生的，但是这个意义并不是很大的，可以发过来几个照片看看？",
            "Cut_Doctor_Reply": "病情 / 分析 / ： / 你好 / ， / 目前 / 从 / 你 / 提供 / 的 / 这个 / 情况 / 来看 / 的话 / ， / 意义 / 并 / 不是 / 很大 / 的 / ， / 你 / 不必 / 太 / 担心 / 的 / ， / 目前 / 你 / 都 / 是 / 怎么 / 治疗 / 的 / ？ / 治疗 / 效果 / 呢 / ？ / 指导 / 意见 / ： / 要 / 是从 / 你 / 提供 / 的 / 这个 / 情况 / 来看 / 的话 / ， / 建议 / 你 / 不要 / 吃 / 花生 / 的 / ， / 但是 / 这个 / 意义 / 并 / 不是 / 很大 / 的 / ， / 可以 / 发过来 / 几个 / 照片 / 看看 / ？",
            "Count_Medical_Des": "0",
            "Word_Medical_Desc": "",
            "Count_Desease_Des": "0",
            "Word_Desease_Desc": ""
        },
        {
            "Doctor_Reply": "您好，根据提供的数据显示孩子是过敏体质，对花生产生过敏。孩子还小，肤质娇嫩敏感，无论是皮肤特点还是肠胃消化吸收系统还未发育完善，易对外界物质产生刺激。平时在饮食护理等方面要多注意些，湿疹有遇热复发的特点，平时不要热到或者捂到孩子，尽量避开过敏源。建议选择婴幼儿湿疹过敏专用的草本植物外用乳膏杏璞霜儿童型进行修复治疗，希望我的回答对你有帮助。以上是对“3个月大的婴儿过敏源检查，看下结果如何”这个问题的建议，希望对您有帮助，祝您健康！",
            "Cut_Doctor_Reply": "您好 / ， / 根据 / 提供 / 的 / 数据 / 显示 / 孩子 / 是 / 过敏 / 体质 / ， / 对 / 花生 / 产生 / 过敏 / 。 / 孩子 / 还 / 小 / ， / 肤质 / 娇嫩 / 敏感 / ， / 无论是 / 皮肤 / 特点 / 还是 / 肠胃 / 消化吸收 / 系统 / 还 / 未 / 发育 / 完善 / ， / 易 / 对 / 外界 / 物质 / 产生 / 刺激 / 。 / 平时 / 在 / 饮食 / 护理 / 等 / 方面 / 要 / 多 / 注意 / 些 / ， / 湿疹 / 有 / 遇热 / 复发 / 的 / 特点 / ， / 平时 / 不要 / 热到 / 或者 / 捂到 / 孩子 / ， / 尽量 / 避开 / 过敏源 / 。 / 建议 / 选择 / 婴幼儿 / 湿疹 / 过敏 / 专用 / 的 / 草本植物 / 外用 / 乳膏 / 杏璞 / 霜 / 儿童 / 型 / 进行 / 修复 / 治疗 / ， / 希望 / 我 / 的 / 回答 / 对 / 你 / 有 / 帮助 / 。 / 以上 / 是 / 对 / “ / 3 / 个 / 月 / 大 / 的 / 婴儿 / 过敏源 / 检查 / ， / 看 / 下 / 结果 / 如何 / ” / 这个 / 问题 / 的 / 建议 / ， / 希望 / 对 / 您 / 有 / 帮助 / ， / 祝您健康 / ！",
            "Count_Medical_Des": "0",
            "Word_Medical_Desc": "",
            "Count_Desease_Des": "0",
            "Word_Desease_Desc": ""
        },
        {
            "Doctor_Reply": "病情分析：你好，根据情况看来小孩可能对花生过敏指导意见：免疫球蛋白有点偏低，说民免疫力稍差，但还是没有什么大问题",
            "Cut_Doctor_Reply": "病情 / 分析 / ： / 你好 / ， / 根据 / 情况 / 看来 / 小孩 / 可能 / 对 / 花生 / 过敏 / 指导 / 意见 / ： / 免疫 / 球蛋白 / 有点 / 偏低 / ， / 说民 / 免疫力 / 稍差 / ， / 但 / 还是 / 没有 / 什么 / 大 / 问题",
            "Count_Medical_Des": "0",
            "Word_Medical_Desc": "",
            "Count_Desease_Des": "0",
            "Word_Desease_Desc": ""
        }
    ]
}