{
    "json_file_name": "F:\\Ask_Information\\妇产科\\妇科\\其它\\https_$$www.120ask.com$question$60000973.htm.json",
    "Description": "子宫内膜息肉宫腔镜手术二十二天可以冲洗阴道吗",
    "Cut_Description": "子宫 / 内膜 / 息肉 / 宫腔镜 / 手术 / 二十二 / 天 / 可以 / 冲洗 / 阴道 / 吗",
    "Count_Medical_Des": "0",
    "Word_Medical_Desc": "",
    "Count_Desease_Des": "0",
    "Word_Desease_Desc": "",
    "Reply_Information": [
        {
            "Doctor_Reply": "病情分析：子宫内膜息肉宫腔镜手术后二十二天是如果阴道没有出血，不是月经期是可以冲洗阴道的。有阴道炎症及时治疗。指导意见：如果是阴道炎症建议先查一下白带常规，看是什么炎症，冲洗阴道后上药治疗，如果乜有什么炎症不建议冲洗阴道。",
            "Cut_Doctor_Reply": "病情 / 分析 / ： / 子宫 / 内膜 / 息肉 / 宫腔镜 / 手术 / 后 / 二十二 / 天是 / 如果 / 阴道 / 没有 / 出血 / ， / 不是 / 月经期 / 是 / 可以 / 冲洗 / 阴道 / 的 / 。 / 有 / 阴道 / 炎症 / 及时 / 治疗 / 。 / 指导 / 意见 / ： / 如果 / 是 / 阴道 / 炎症 / 建议 / 先查 / 一下 / 白带 / 常规 / ， / 看 / 是 / 什么 / 炎症 / ， / 冲洗 / 阴道 / 后 / 上药 / 治疗 / ， / 如果 / 乜有 / 什么 / 炎症 / 不 / 建议 / 冲洗 / 阴道 / 。",
            "Count_Medical_Des": "0",
            "Word_Medical_Desc": "",
            "Count_Desease_Des": "0",
            "Word_Desease_Desc": ""
        },
        {
            "Doctor_Reply": "病情分析：治疗方案：根据息肉的大小、位置、形态及患者的年龄，采取不同的治法。1．对于较大而有蒂的息肉，可在子宫下段见到或摸到，此时可通过扩张宫颈将息肉摘除，然后进行宫颈及宫腔搔刮术，将其余息肉刮出并送病理检查。指导意见：2．小型局灶型或弥漫型息肉行刮宫术，应注意全面搔刮，尤其是宫底及宫角处3．宫腔手术后，应进行抗感染治疗。临床可给予抗生素类药物口服或静点。4．对出血症状明显，按上述方法治疗未能根除或经常复发者，应考虑行子宫切除。",
            "Cut_Doctor_Reply": "病情 / 分析 / ： / 治疗 / 方案 / ： / 根据 / 息肉 / 的 / 大小 / 、 / 位置 / 、 / 形态 / 及 / 患者 / 的 / 年龄 / ， / 采取 / 不同 / 的 / 治法 / 。 / 1 / ． / 对于 / 较大 / 而 / 有 / 蒂 / 的 / 息肉 / ， / 可 / 在 / 子宫 / 下 / 段 / 见到 / 或 / 摸 / 到 / ， / 此时 / 可 / 通过 / 扩张 / 宫颈 / 将 / 息肉 / 摘除 / ， / 然后 / 进行 / 宫颈 / 及 / 宫腔 / 搔 / 刮术 / ， / 将 / 其余 / 息肉 / 刮出 / 并 / 送 / 病理 / 检查 / 。 / 指导 / 意见 / ： / 2 / ． / 小型 / 局灶型 / 或 / 弥漫型 / 息肉 / 行 / 刮宫 / 术 / ， / 应 / 注意 / 全面 / 搔 / 刮 / ， / 尤其 / 是 / 宫底 / 及 / 宫角处 / 3 / ． / 宫腔 / 手术 / 后 / ， / 应 / 进行 / 抗感染 / 治疗 / 。 / 临床 / 可 / 给予 / 抗生素 / 类药物 / 口服 / 或静点 / 。 / 4 / ． / 对 / 出血 / 症状 / 明显 / ， / 按 / 上述 / 方法 / 治疗 / 未能 / 根除 / 或 / 经常 / 复发 / 者 / ， / 应 / 考虑 / 行 / 子宫 / 切除 / 。",
            "Count_Medical_Des": "0",
            "Word_Medical_Desc": "",
            "Count_Desease_Des": "0",
            "Word_Desease_Desc": ""
        }
    ]
}