{
    "json_file_name": "F:\\Ask_Information\\心理健康科\\失眠\\其它\\https_$$www.120ask.com$question$60000185.htm.json",
    "Description": "这次来月经，前一天就感觉自己很压抑，爱胡思乱想一些不好的事，睡眠也不太好，第一天来月经就觉得好多了，不会那么压抑，但是有时候还是会胡思乱想，不知道是不是月经来的关系，有点担心。",
    "Cut_Description": "这次 / 来 / 月经 / ， / 前一天 / 就 / 感觉 / 自己 / 很 / 压抑 / ， / 爱 / 胡思乱想 / 一些 / 不好 / 的 / 事 / ， / 睡眠 / 也 / 不太好 / ， / 第一天 / 来 / 月经 / 就 / 觉得 / 好多 / 了 / ， / 不会 / 那么 / 压抑 / ， / 但是 / 有时候 / 还是 / 会 / 胡思乱想 / ， / 不 / 知道 / 是不是 / 月经 / 来 / 的 / 关系 / ， / 有点 / 担心 / 。",
    "Count_Medical_Des": "0",
    "Word_Medical_Desc": "",
    "Count_Desease_Des": "0",
    "Word_Desease_Desc": "",
    "Reply_Information": [
        {
            "Doctor_Reply": "病情分析：你的描述考虑是心理性，指导意见：你好，这个问题临床一般建议休息，建议保持乐观，减少不良刺激。",
            "Cut_Doctor_Reply": "病情 / 分析 / ： / 你 / 的 / 描述 / 考虑 / 是 / 心理 / 性 / ， / 指导 / 意见 / ： / 你好 / ， / 这个 / 问题 / 临床 / 一般 / 建议 / 休息 / ， / 建议 / 保持 / 乐观 / ， / 减少 / 不良 / 刺激 / 。",
            "Count_Medical_Des": "0",
            "Word_Medical_Desc": "",
            "Count_Desease_Des": "0",
            "Word_Desease_Desc": ""
        },
        {
            "Doctor_Reply": "病情分析：你好，你这次来月经，前一天就感觉自己很压抑，爱胡思乱想一些不好的事，睡眠也不太好，第一天来月经就觉得好多了，不会那么压抑，但是有时候还是会胡思乱想，不知道是不是月经来的关系，有点担心。你是经前焦虑症的症状。指导意见：建议你平时多食用清淡的食物，不要食用辛辣的食物，天天进行一小时的有氧运动，保持情绪的稳定，多与人沟通交往，你会改善的。",
            "Cut_Doctor_Reply": "病情 / 分析 / ： / 你好 / ， / 你 / 这次 / 来 / 月经 / ， / 前一天 / 就 / 感觉 / 自己 / 很 / 压抑 / ， / 爱 / 胡思乱想 / 一些 / 不好 / 的 / 事 / ， / 睡眠 / 也 / 不太好 / ， / 第一天 / 来 / 月经 / 就 / 觉得 / 好多 / 了 / ， / 不会 / 那么 / 压抑 / ， / 但是 / 有时候 / 还是 / 会 / 胡思乱想 / ， / 不 / 知道 / 是不是 / 月经 / 来 / 的 / 关系 / ， / 有点 / 担心 / 。 / 你 / 是 / 经前 / 焦虑症 / 的 / 症状 / 。 / 指导 / 意见 / ： / 建议 / 你 / 平时 / 多 / 食用 / 清淡 / 的 / 食物 / ， / 不要 / 食用 / 辛辣 / 的 / 食物 / ， / 天天 / 进行 / 一 / 小时 / 的 / 有氧 / 运动 / ， / 保持 / 情绪 / 的 / 稳定 / ， / 多 / 与 / 人 / 沟通 / 交往 / ， / 你 / 会 / 改善 / 的 / 。",
            "Count_Medical_Des": "0",
            "Word_Medical_Desc": "",
            "Count_Desease_Des": "0",
            "Word_Desease_Desc": ""
        },
        {
            "Doctor_Reply": "病情分析：姑娘你好，不知道你这样的情况之前来月经之前有没有，如果也有，那就应该是经前期综合征的表现指导意见：经前期注意保暖，适度休息，喝点红糖姜水，不要劳累和着凉，有紧张情绪的时候注意放松自己，分散一下注意力，不要担心，稍微注意一下就可以了，姑娘以上是对“月经期间很压抑，爱胡思乱想，睡眠不太好”这个问题的建议，希望对您有帮助，祝您健康！",
            "Cut_Doctor_Reply": "病情 / 分析 / ： / 姑娘 / 你好 / ， / 不 / 知道 / 你 / 这样 / 的 / 情况 / 之前 / 来 / 月经 / 之前 / 有没有 / ， / 如果 / 也 / 有 / ， / 那 / 就 / 应该 / 是 / 经 / 前期 / 综合征 / 的 / 表现 / 指导 / 意见 / ： / 经 / 前期 / 注意 / 保暖 / ， / 适度 / 休息 / ， / 喝点 / 红糖 / 姜水 / ， / 不要 / 劳累 / 和 / 着凉 / ， / 有 / 紧张 / 情绪 / 的 / 时候 / 注意 / 放松 / 自己 / ， / 分散 / 一下 / 注意力 / ， / 不要 / 担心 / ， / 稍微 / 注意 / 一下 / 就 / 可以 / 了 / ， / 姑娘 / 以上 / 是 / 对 / “ / 月经 / 期间 / 很 / 压抑 / ， / 爱 / 胡思乱想 / ， / 睡眠 / 不太好 / ” / 这个 / 问题 / 的 / 建议 / ， / 希望 / 对 / 您 / 有 / 帮助 / ， / 祝您健康 / ！",
            "Count_Medical_Des": "0",
            "Word_Medical_Desc": "",
            "Count_Desease_Des": "0",
            "Word_Desease_Desc": ""
        },
        {
            "Doctor_Reply": "病情分析：根据你上面提供的信息，来月经的时候容易胡思乱想的。来月经的前1天。感觉自己有点压抑。睡眠也不太好。不知道是不是月经的原因。指导意见：来月经的时候，女友体内的性激素水平撤退。人的情绪是容易低落的。你这种情况可能有月经有关系。但是注意，学会转移注意就行了。",
            "Cut_Doctor_Reply": "病情 / 分析 / ： / 根据 / 你 / 上面 / 提供 / 的 / 信息 / ， / 来 / 月经 / 的 / 时候 / 容易 / 胡思乱想 / 的 / 。 / 来 / 月经 / 的 / 前 / 1 / 天 / 。 / 感觉 / 自己 / 有点 / 压抑 / 。 / 睡眠 / 也 / 不太好 / 。 / 不 / 知道 / 是不是 / 月经 / 的 / 原因 / 。 / 指导 / 意见 / ： / 来 / 月经 / 的 / 时候 / ， / 女友 / 体内 / 的 / 性激素 / 水平 / 撤退 / 。 / 人 / 的 / 情绪 / 是 / 容易 / 低落 / 的 / 。 / 你 / 这种 / 情况 / 可能 / 有 / 月经 / 有 / 关系 / 。 / 但是 / 注意 / ， / 学会 / 转移 / 注意 / 就行了 / 。",
            "Count_Medical_Des": "0",
            "Word_Medical_Desc": "",
            "Count_Desease_Des": "0",
            "Word_Desease_Desc": ""
        },
        {
            "Doctor_Reply": "病情分析：您好，失眠的症状主要跟用脑过度，过度劳累，心情烦躁等因素有关的，指导意见：可以使用安神补脑液和甲钴胺胶囊进行治疗较好，平时要多吃坚果类食物，例如核桃，葵花籽等，调整自己的作息习惯，避免劳累，",
            "Cut_Doctor_Reply": "病情 / 分析 / ： / 您好 / ， / 失眠 / 的 / 症状 / 主要 / 跟 / 用脑 / 过度 / ， / 过度 / 劳累 / ， / 心情 / 烦躁 / 等 / 因素 / 有关 / 的 / ， / 指导 / 意见 / ： / 可以 / 使用 / 安神 / 补 / 脑液 / 和 / 甲 / 钴 / 胺 / 胶囊 / 进行 / 治疗 / 较 / 好 / ， / 平时 / 要 / 多 / 吃 / 坚果 / 类 / 食物 / ， / 例如 / 核桃 / ， / 葵花籽 / 等 / ， / 调整 / 自己 / 的 / 作息 / 习惯 / ， / 避免 / 劳累 / ，",
            "Count_Medical_Des": "0",
            "Word_Medical_Desc": "",
            "Count_Desease_Des": "0",
            "Word_Desease_Desc": ""
        }
    ]
}