{
    "json_file_name": "F:\\Ask_Information\\肿瘤科\\腹部肿瘤\\食管癌\\https_$$www.120ask.com$question$60000942.htm.json",
    "Description": "我父親今年六十岁了，前个月声音突然吵哑，去医院检查是食管癌，请問这应該怎樣治療",
    "Cut_Description": "我 / 父親 / 今年 / 六十岁 / 了 / ， / 前个 / 月 / 声音 / 突然 / 吵哑 / ， / 去 / 医院 / 检查 / 是 / 食管癌 / ， / 请問 / 这应 / 該 / 怎樣 / 治療",
    "Count_Medical_Des": "0",
    "Word_Medical_Desc": "",
    "Count_Desease_Des": "0",
    "Word_Desease_Desc": "",
    "Reply_Information": [
        {
            "Doctor_Reply": "病情分析：这个情况首先首先考虑使用手术治疗，指导意见：如果不能手术治疗，可以用放化疗，结合中医治疗，中医治疗可以降低化疗的副作用，提高疗效。",
            "Cut_Doctor_Reply": "病情 / 分析 / ： / 这个 / 情况 / 首先 / 首先 / 考虑 / 使用 / 手术 / 治疗 / ， / 指导 / 意见 / ： / 如果 / 不能 / 手术 / 治疗 / ， / 可以 / 用 / 放化疗 / ， / 结合 / 中医 / 治疗 / ， / 中医 / 治疗 / 可以 / 降低 / 化疗 / 的 / 副作用 / ， / 提高 / 疗效 / 。",
            "Count_Medical_Des": "0",
            "Word_Medical_Desc": "",
            "Count_Desease_Des": "0",
            "Word_Desease_Desc": ""
        },
        {
            "Doctor_Reply": "病情分析：食道癌的治疗方案：一到胸外科进行手术切除，达到根治的目的，也是最佳治疗方案，二化学药物治疗，防止发生转移，三放射治疗，术前可使肿瘤缩小，四中医中药治疗。指导意见：食道癌的治疗方案：一到胸外科进行手术切除，达到根治的目的，也是最佳治疗方案，二化学药物治疗，防止发生转移，三放射治疗，术前可使肿瘤缩小，四中医中药治疗。",
            "Cut_Doctor_Reply": "病情 / 分析 / ： / 食道癌 / 的 / 治疗 / 方案 / ： / 一到 / 胸外科 / 进行 / 手术 / 切除 / ， / 达到 / 根治 / 的 / 目的 / ， / 也 / 是 / 最佳 / 治疗 / 方案 / ， / 二 / 化学 / 药物 / 治疗 / ， / 防止 / 发生 / 转移 / ， / 三 / 放射治疗 / ， / 术前 / 可 / 使 / 肿瘤 / 缩小 / ， / 四 / 中医中药 / 治疗 / 。 / 指导 / 意见 / ： / 食道癌 / 的 / 治疗 / 方案 / ： / 一到 / 胸外科 / 进行 / 手术 / 切除 / ， / 达到 / 根治 / 的 / 目的 / ， / 也 / 是 / 最佳 / 治疗 / 方案 / ， / 二 / 化学 / 药物 / 治疗 / ， / 防止 / 发生 / 转移 / ， / 三 / 放射治疗 / ， / 术前 / 可 / 使 / 肿瘤 / 缩小 / ， / 四 / 中医中药 / 治疗 / 。",
            "Count_Medical_Des": "0",
            "Word_Medical_Desc": "",
            "Count_Desease_Des": "0",
            "Word_Desease_Desc": ""
        },
        {
            "Doctor_Reply": "病情分析：你好;食管癌早期的治疗应该是应该采用手术，指导意见：放化疗，中医药治疗相结合的综合治疗方式，中晚期就要采用中医保守治疗，以上是对“请問这类食管癌应怎麽樣治療最佳”这个问题的建议，希望对您有帮助，祝您健康！",
            "Cut_Doctor_Reply": "病情 / 分析 / ： / 你好 / ; / 食管癌 / 早期 / 的 / 治疗 / 应该 / 是 / 应该 / 采用 / 手术 / ， / 指导 / 意见 / ： / 放化疗 / ， / 中医药 / 治疗 / 相结合 / 的 / 综合 / 治疗 / 方式 / ， / 中晚期 / 就要 / 采用 / 中医 / 保守 / 治疗 / ， / 以上 / 是 / 对 / “ / 请問 / 这类 / 食管癌 / 应 / 怎 / 麽 / 樣 / 治療 / 最佳 / ” / 这个 / 问题 / 的 / 建议 / ， / 希望 / 对 / 您 / 有 / 帮助 / ， / 祝您健康 / ！",
            "Count_Medical_Des": "0",
            "Word_Medical_Desc": "",
            "Count_Desease_Des": "0",
            "Word_Desease_Desc": ""
        },
        {
            "Doctor_Reply": "病情分析：您好，根据患者症状建议采用下面的方法治疗。指导意见：建议：食道癌早期，手术切除再辅以放疗治疗或中医药治疗效果最好。对于中晚期患者来说，在选择时要慎重。放疗结合中医药在治疗中晚期食道癌方面有着自己独特的优势。经过高精度定位仪模拟定位机和物理治疗仪双重精密定位后，再量身定制最适合的放疗方案，可直接、快速的抑制、消融肿瘤实质，有效阻止肿瘤细胞无限制克隆性增生，抑制肿瘤浸润生长，减小出现恶化、转移、癌侵犯的可能性。再辅以特制分子靶向中药消除治疗不良反应，有效延长患者生命。",
            "Cut_Doctor_Reply": "病情 / 分析 / ： / 您好 / ， / 根据 / 患者 / 症状 / 建议 / 采用 / 下面 / 的 / 方法 / 治疗 / 。 / 指导 / 意见 / ： / 建议 / ： / 食道癌 / 早期 / ， / 手术 / 切除 / 再 / 辅以 / 放疗 / 治疗 / 或 / 中医药 / 治疗 / 效果 / 最好 / 。 / 对于 / 中晚期 / 患者 / 来说 / ， / 在 / 选择 / 时要 / 慎重 / 。 / 放疗 / 结合 / 中医药 / 在 / 治疗 / 中晚期 / 食道癌 / 方面 / 有着 / 自己 / 独特 / 的 / 优势 / 。 / 经过 / 高精度 / 定位仪 / 模拟 / 定位 / 机和 / 物理 / 治疗仪 / 双重 / 精密 / 定位 / 后 / ， / 再 / 量身 / 定制 / 最 / 适合 / 的 / 放疗 / 方案 / ， / 可 / 直接 / 、 / 快速 / 的 / 抑制 / 、 / 消融 / 肿瘤 / 实质 / ， / 有效 / 阻止 / 肿瘤 / 细胞 / 无 / 限制 / 克隆 / 性 / 增生 / ， / 抑制 / 肿瘤 / 浸润 / 生长 / ， / 减小 / 出现 / 恶化 / 、 / 转移 / 、 / 癌 / 侵犯 / 的 / 可能性 / 。 / 再 / 辅以 / 特制 / 分子 / 靶向 / 中药 / 消除 / 治疗 / 不良反应 / ， / 有效 / 延长 / 患者 / 生命 / 。",
            "Count_Medical_Des": "0",
            "Word_Medical_Desc": "",
            "Count_Desease_Des": "0",
            "Word_Desease_Desc": ""
        }
    ]
}